{"6223815012ec5ae5e83ac14f1fdf79ef": [{"n": 1, "text": "ein sch\u00f6nes Ferienhaus, welches toll eingerichtet war", "bounds": [31, 84]}, {"n": 1, "text": "wunderbar", "bounds": [147, 156]}, {"n": 1, "text": "laute, dr\u00f6hnende Musik mit unfassbarem Bass anh\u00f6ren", "bounds": [295, 346]}, {"n": 1, "text": "Dieses Privatkonzert war selbst bis ins Haus bei geschlossenen Fenster zu h\u00f6ren", "bounds": [512, 591]}], "0d26258c4e9d7cb1f4fba2399f4b09d9": [{"n": 1, "text": "Haus sehr gut", "bounds": [0, 13]}, {"n": 1, "text": "Besenreine \u00dcbergabe", "bounds": [49, 68]}, {"n": 1, "text": "Schlechte Parkm\u00f6glichkeiten.", "bounds": [81, 109]}], "5e4f3544eaa1dade199baa306c78ba16": [{"n": 1, "text": "Tolles Haus", "bounds": [0, 11]}, {"n": 1, "text": "Immer wieder.", "bounds": [35, 48]}], "341b6dd700fde1fe1f53087d1151204f": [{"n": 1, "text": "Top Ferienhaus", "bounds": [0, 14]}], "de723d8e3846821f0d08ae30f2367560": [{"n": 1, "text": "Gartenm\u00f6bel (Liegen)", "bounds": [4, 24]}, {"n": 1, "text": "Insgesamt ist es darin eher unordentlich.", "bounds": [73, 114]}], "38e077cd30683692790bfd281acab131": [{"n": 1, "text": "Wir haben uns sehr wohl gef\u00fchlt", "bounds": [0, 31]}, {"n": 1, "text": "noch vor unserer R\u00fcckreise entschlossen, eine Woche im September 2024 wieder in dem wundersch\u00f6nen Ferienhaus zu verbringen.", "bounds": [47, 170]}, {"n": 1, "text": "100 % Weiterempfehlung", "bounds": [191, 213]}], "fc14bdd9a89b70c6ef04071ddac47273": [{"n": 1, "text": "jederzeit wieder gehen", "bounds": [25, 47]}, {"n": 1, "text": "ruhig", "bounds": [58, 63]}, {"n": 1, "text": "entfernt", "bounds": [97, 105]}], "cb436491dc76dd53b18e578a21dc669d": [{"n": 1, "text": "Schlafzimmer im Erdgeschoss mit eigenem Badezimmer", "bounds": [95, 145]}, {"n": 1, "text": "\"Poppi-Mobil\" (Tankstelle Poppinga gegen\u00fcber der Zwillingsm\u00fchlen)", "bounds": [156, 221]}], "9d70b0eb0154908654bd95d997f999a2": [{"n": 1, "text": "Im liebevoll eingerichteten Fischers Fritz f\u00fchlen wir uns sofort wie zu Hause", "bounds": [0, 77]}, {"n": 1, "text": "Sowohl an sonnigen als auch an regnerischen Tagen l\u00e4sst es sich hier perfekt aushalten.", "bounds": [124, 211]}, {"n": 1, "text": "nicht zu sehr im Trubel, aber alles gut zu Fu\u00df oder mit dem Fahrrad zu erreichen.", "bounds": [242, 323]}], "b713365b64c61c866ed158306a65746a": [{"n": 1, "text": "War ein reibungsloser sehr netter Ablauf", "bounds": [0, 40]}, {"n": 1, "text": "sehr sehr sch\u00f6n", "bounds": [52, 67]}, {"n": 1, "text": "hochwertig eingerichtet", "bounds": [72, 95]}], "5f0612f3a1546a162665a20f828b0778": [{"n": 1, "text": "Toll eingerichtetes Haus", "bounds": [0, 24]}, {"n": 1, "text": "super gefallen", "bounds": [57, 71]}], "424c51b13f8f43ce707e4252c0c83174": [{"n": 1, "text": "rundherum wohlgef\u00fchlt!", "bounds": [104, 126]}, {"n": 1, "text": "sehr sauber", "bounds": [140, 151]}, {"n": 1, "text": "alles da, was man braucht.", "bounds": [163, 189]}, {"n": 1, "text": "allen Fragen/Anliegen weiterhelfen konnte.", "bounds": [238, 280]}, {"n": 1, "text": "auf jeden Fall wieder!", "bounds": [292, 314]}], "e530557b2c1270213a6eadff43801315": [{"n": 1, "text": "Nur Positive Eindr\u00fccke", "bounds": [0, 22]}, {"n": 1, "text": "sch\u00f6nen Objekt", "bounds": [34, 48]}], "05dfc4e8d9fb299bc86c4a34a5090989": [{"n": 1, "text": "Alles super", "bounds": [0, 11]}], "af30f1bd76d6de4519923335925995bc": [], "199a857d33d50b6374c0ee2cce3c493f": [{"n": 1, "text": "Modern", "bounds": [0, 6]}, {"n": 1, "text": "eine super Ausstattung", "bounds": [11, 33]}], "21a85998bec8fe83d0167f0eebc02dc3": [{"n": 1, "text": "Fischers Fritz entsprach genau unseren Vorstellungen von einem Ferienhaus.", "bounds": [0, 74]}, {"n": 1, "text": "sehr modern und liebevoll eingerichtet", "bounds": [82, 120]}, {"n": 1, "text": "Wir haben uns rundum wohlgef\u00fchlt", "bounds": [158, 190]}], "86be29e007c9bd38b1cea3ec7bf3a531": [{"n": 1, "text": "Das Haus ist sehr sch\u00f6n", "bounds": [0, 23]}, {"n": 1, "text": "gem\u00fctlich", "bounds": [28, 37]}, {"n": 1, "text": "sehr wohl gef\u00fchlt", "bounds": [65, 82]}, {"n": 1, "text": "Ein sehr sch\u00f6ner Urlaub", "bounds": [84, 107]}], "1a5faec21f3b67717b78a7569002d350": [{"n": 1, "text": "wundersch\u00f6nen Haus", "bounds": [29, 47]}, {"n": 1, "text": "Alles war top gepflegt.", "bounds": [90, 113]}, {"n": 1, "text": "tollen neuwertigen Fahrr\u00e4dern", "bounds": [184, 213]}, {"n": 1, "text": "bestens gepflegt.", "bounds": [268, 285]}, {"n": 1, "text": "sehr wohl gef\u00fchlt.", "bounds": [300, 318]}], "55c3cd1bc8c79c2fe8375a161048fc32": [{"n": 1, "text": "sehr sch\u00f6ne Osterferienwoche", "bounds": [15, 43]}, {"n": 1, "text": "sehr sauber", "bounds": [86, 97]}, {"n": 1, "text": "toll ausgestattet", "bounds": [102, 119]}, {"n": 1, "text": "bedurfte einer Absprache mit dem Nachbarn", "bounds": [164, 205]}], "6cde9e1440af1a38db1fd1b3623fe082": [{"n": 1, "text": "Wir sind sehr zufrieden!", "bounds": [0, 24]}, {"n": 1, "text": "Vielen Dank f\u00fcr alles.", "bounds": [42, 64]}], "f80be957e15c86c44502c5329229f877": [{"n": 1, "text": "eine tolle Zeit", "bounds": [7, 22]}, {"n": 1, "text": "Wir kommen sicher nochmal wieder.", "bounds": [53, 86]}], "5341c4c808e4051d25141ad99ce27eef": [{"n": 1, "text": "Wir haben uns in diesem tollen Domizil rundum wohl gef\u00fchlt.", "bounds": [0, 59]}, {"n": 1, "text": "liebevoll gestaltet", "bounds": [91, 110]}, {"n": 1, "text": "die bereitgestellten Fahrr\u00e4der", "bounds": [170, 200]}, {"n": 1, "text": "der Weber-Grill", "bounds": [246, 261]}], "7991e23721e136a7ff4f9afd96ec8c5d": [{"n": 1, "text": "sehr wohlgef\u00fchlt", "bounds": [39, 55]}, {"n": 1, "text": "es war alles perfekt", "bounds": [57, 77]}, {"n": 1, "text": "Ein gro\u00dfes Dankesch\u00f6n auch an alle Mitarbeiter", "bounds": [113, 159]}, {"n": 1, "text": "wundersch\u00f6n war", "bounds": [204, 219]}], "ef07c10e379d6fbb657e7ad4376c3a8f": [{"n": 1, "text": "sehr sch\u00f6nes", "bounds": [4, 16]}, {"n": 1, "text": "liebevollen Details", "bounds": [21, 40]}, {"n": 1, "text": "Sehr sauber", "bounds": [94, 105]}, {"n": 1, "text": "Betreuung vor Ort", "bounds": [135, 152]}, {"n": 1, "text": "sehr nett", "bounds": [178, 187]}], "d67bdaeba1866b35b96548e0958dce53": [{"n": 1, "text": "Liebevoll und \u00e4u\u00dferst geschmackvoll eingerichtet", "bounds": [102, 150]}, {"n": 1, "text": "Zwei Top-Fahrr\u00e4der sind beim Haus mit dabei", "bounds": [217, 260]}, {"n": 1, "text": "Zu dem ist das Team von Frau Poppens super nett und kompetent!!!", "bounds": [450, 514]}, {"n": 1, "text": "Wir waren rund um zu frieden und werden bestimmt mal wieder kommen!", "bounds": [727, 794]}], "fb2439c3f76fd7576fcfd08fd949bfd1": [{"n": 1, "text": "sehr modern und hochwertig eingerichtet", "bounds": [19, 58]}, {"n": 1, "text": "l\u00e4sst keinerlei W\u00fcnsche offen", "bounds": [111, 140]}, {"n": 1, "text": "perfekt - etwas abseits vom touristischen Trubel", "bounds": [-1, 47]}, {"n": 1, "text": "Wir kommen auf jeden Fall wieder", "bounds": [347, 379]}], "61a95ed1d6b7d00b89032d7e908045e2": [{"n": 1, "text": "wundersch\u00f6ne Ausstattung", "bounds": [39, 63]}, {"n": 1, "text": "100 % den Bildern im Internet", "bounds": [82, 111]}, {"n": 1, "text": "Lage am Ortsrand von Greetsiel ist nur zu empfehlen", "bounds": [-1, 50]}, {"n": 1, "text": "10 Minuten", "bounds": [187, 197]}, {"n": 1, "text": "gebucht", "bounds": [259, 266]}]}